AUTHORS
LICENSE
MANIFEST.in
README.rst
setup.py
test/test_caching.py
test/test_route.py
tornadotools/__init__.py
tornadotools/adisp.py
tornadotools/caching.py
tornadotools/forms.py
tornadotools/route.py
tornadotools.egg-info/PKG-INFO
tornadotools.egg-info/SOURCES.txt
tornadotools.egg-info/dependency_links.txt
tornadotools.egg-info/entry_points.txt
tornadotools.egg-info/requires.txt
tornadotools.egg-info/top_level.txt
tornadotools/mongrel2/__init__.py
tornadotools/mongrel2/handler.py
tornadotools/mongrel2/request.py