Metadata-Version: 1.1
Name: tornadotools
Version: 0.2.2
Summary: A set of tools for working with tornado
Home-page: https://github.com/truemped/tornadotools
Author: Daniel Truemper
Author-email: truemped@googlemail.com
License: Apache 2.0
Platform: UNKNOWN
Classifier: Intended Audience :: Developers
Classifier: Development Status :: 3 - Alpha
Classifier: License :: OSI Approved :: Apache Software License
Classifier: Programming Language :: Python :: 2.6
Classifier: Topic :: Internet :: WWW/HTTP :: HTTP Servers
Classifier: Topic :: Software Development :: Libraries :: Application Frameworks
Classifier: Topic :: Software Development :: Libraries :: Python Modules
